MC6809/__init__.py
MC6809/__main__.py
MC6809/constants.py
MC6809/example6809.py
MC6809/cli_app/__init__.py
MC6809/cli_app/mc6809.py
MC6809/cli_dev/__init__.py
MC6809/cli_dev/code_style.py
MC6809/cli_dev/packaging.py
MC6809/cli_dev/testing.py
MC6809/cli_dev/update_readme_history.py
MC6809/components/__init__.py
MC6809/components/cpu6809.py
MC6809/components/cpu6809_html_debug.py
MC6809/components/cpu6809_trace.py
MC6809/components/mc6809_addressing.py
MC6809/components/mc6809_base.py
MC6809/components/mc6809_cc_register.py
MC6809/components/mc6809_interrupt.py
MC6809/components/mc6809_ops_branches.py
MC6809/components/mc6809_ops_load_store.py
MC6809/components/mc6809_ops_logic.py
MC6809/components/mc6809_ops_test.py
MC6809/components/mc6809_speedlimited.py
MC6809/components/mc6809_stack.py
MC6809/components/mc6809_tools.py
MC6809/components/memory.py
MC6809/components/MC6809data/CPU6809_HTML_export.py
MC6809/components/MC6809data/CPU6809_opcodes.csv
MC6809/components/MC6809data/CPU6809_opcodes.html
MC6809/components/MC6809data/CPU6809csv_export.py
MC6809/components/MC6809data/MC6809_data_utils.py
MC6809/components/MC6809data/MC6809_op_data.py
MC6809/components/MC6809data/MC6809_op_docs.py
MC6809/components/MC6809data/__init__.py
MC6809/components/cpu_utils/Instruction_generator.py
MC6809/components/cpu_utils/MC6809_registers.py
MC6809/components/cpu_utils/__init__.py
MC6809/components/cpu_utils/instruction_base.py
MC6809/components/cpu_utils/instruction_call.py
MC6809/components/cpu_utils/instruction_caller.py
MC6809/core/__init__.py
MC6809/core/benchmark.py
MC6809/core/configs.py
MC6809/core/cpu_control_server.py
MC6809/core/memory_info.py
MC6809/tests/CPU6809_opcodes.html
MC6809/tests/LST2Unittest.py
MC6809/tests/__init__.py
MC6809/tests/test_6809_StoreLoad.py
MC6809/tests/test_6809_address_modes.py
MC6809/tests/test_6809_arithmetic.py
MC6809/tests/test_6809_arithmetic_shift.py
MC6809/tests/test_6809_branch_instructions.py
MC6809/tests/test_6809_program.py
mc6809-0.8.0.dist-info/METADATA
mc6809-0.8.0.dist-info/WHEEL
mc6809-0.8.0.dist-info/entry_points.txt
mc6809-0.8.0.dist-info/licenses/AUTHORS
mc6809-0.8.0.dist-info/licenses/LICENSE
mc6809-0.8.0.dist-info/RECORD
