Metadata-Version: 2.4
Name: MC6809
Version: 0.8.0
Summary: MC6809 CPU emulator written in Python
Project-URL: Documentation, https://github.com/6809/MC6809
Project-URL: Source, https://github.com/6809/MC6809
Author-email: Jens Diemer <git@jensdiemer.de>
License: GPL-3.0-or-later
License-File: AUTHORS
License-File: LICENSE
Requires-Python: >=3.11
Requires-Dist: bx-py-utils
Requires-Dist: cli-base-utilities
Requires-Dist: rich
Requires-Dist: tyro
